package_crypto/__init__.py
package_crypto-0.0.9.dist-info/LICENCE.txt
package_crypto-0.0.9.dist-info/METADATA
package_crypto-0.0.9.dist-info/WHEEL
package_crypto-0.0.9.dist-info/top_level.txt
package_crypto-0.0.9.dist-info/RECORD
