Metadata-Version: 2.1
Name: package-crypto
Version: 0.0.9
Summary: This package is for getting all the paragraphs related to specific cryptocurrencies
Home-page: UNKNOWN
Author: Taukenov Assylken
Author-email: asylken02@gmail.com
License: MIT
Keywords: crypto parsing
Platform: UNKNOWN
License-File: LICENCE.txt
Requires-Dist: beautifulsoup4 (==4.10.0)
Requires-Dist: requests (==2.26.0)
Requires-Dist: html5lib (==1.1)
